AUTHORS
LICENSE
MANIFEST.in
README.md
setup.py
announcements/__init__.py
announcements/admin.py
announcements/auth_backends.py
announcements/forms.py
announcements/models.py
announcements/signals.py
announcements/urls.py
announcements/views.py
announcements/templates/announcements/announcement_confirm_delete.html
announcements/templates/announcements/announcement_form.html
announcements/templates/announcements/announcement_list.html
announcements/templates/announcements/base.html
announcements/templatetags/__init__.py
announcements/templatetags/announcements_tags.py
django_announcements.egg-info/PKG-INFO
django_announcements.egg-info/SOURCES.txt
django_announcements.egg-info/dependency_links.txt
django_announcements.egg-info/not-zip-safe
django_announcements.egg-info/top_level.txt
docs/Makefile
docs/changelog.rst
docs/conf.py
docs/index.rst
docs/installation.rst
docs/templatetags.rst
docs/usage.rst