Metadata-Version: 1.1
Name: django-announcements
Version: 1.2.0
Summary: Announcements for your Django powered website.
Home-page: https://github.com/pinax/django-announcements
Author: Brian Rosner
Author-email: brosner@gmail.com
License: MIT
Platform: UNKNOWN
Classifier: Development Status :: 5 - Production/Stable
Classifier: Environment :: Web Environment
Classifier: Intended Audience :: Developers
Classifier: License :: OSI Approved :: MIT License
Classifier: Operating System :: OS Independent
Classifier: Programming Language :: Python
Classifier: Framework :: Django
